{"cameraMode":{"drawMode":0,"name":"Shaded","section":"Shading Mode"},"sceneLighting":true,"audioPlay":false,"sceneViewState":{"m_AlwaysRefresh":false,"showFog":true,"showSkybox":true,"showFlares":true,"showImageEffects":true,"showParticleSystems":true,"showVisualEffectGraphs":true,"m_FxEnabled":true},"in2DMode":false,"pivot":{"x":3.112863063812256,"y":-32.604156494140628,"z":420.9825134277344},"rotation":{"x":-0.378762811422348,"y":-0.03830213472247124,"z":0.015691040083765985,"w":-0.9245702028274536},"size":29.08527183532715,"orthographic":false}